{
  "project_info": {
    "project_number": "319714964156",
    "project_id": "recipeapp-caf40",
    "storage_bucket": "recipeapp-caf40.appspot.com"
  },
  "client": [
    {
      "client_info": {
        "mobilesdk_app_id": "1:319714964156:android:7ccde48effbbcd18b656b9",
        "android_client_info": {
          "package_name": "com.example.recipe1"
        }
      },
      "oauth_client": [
        {
          "client_id": "319714964156-vpkgj2887rbrb7bcoiao9hchkf9hheug.apps.googleusercontent.com",
          "client_type": 3
        }
      ],
      "api_key": [
        {
          "current_key": "AIzaSyDbWCwvHE76Ll0egZmXIEPBBexvdIcLDGA"
        }
      ],
      "services": {
        "appinvite_service": {
          "other_platform_oauth_client": [
            {
              "client_id": "319714964156-vpkgj2887rbrb7bcoiao9hchkf9hheug.apps.googleusercontent.com",
              "client_type": 3
            }
          ]
        }
      }
    }
  ],
  "configuration_version": "1"
}